{
	"name": "pipelinePremier",
	"properties": {
		"activities": [
			{
				"name": "dataflowDatesEtHeures",
				"type": "ExecuteDataFlow",
				"dependsOn": [],
				"policy": {
					"timeout": "7.00:00:00",
					"retry": 0,
					"retryIntervalInSeconds": 30,
					"secureOutput": false,
					"secureInput": false
				},
				"userProperties": [],
				"typeProperties": {
					"dataflow": {
						"referenceName": "dataflowDatesEtHeures",
						"type": "DataFlowReference"
					},
					"compute": {
						"coreCount": 8,
						"computeType": "General"
					}
				}
			},
			{
				"name": "TestMonTexte",
				"type": "IfCondition",
				"dependsOn": [
					{
						"activity": "dataflowDatesEtHeures",
						"dependencyConditions": [
							"Succeeded"
						]
					}
				],
				"userProperties": [],
				"typeProperties": {
					"expression": {
						"value": "@equals(variables('MonTexte'),'truc')",
						"type": "Expression"
					},
					"ifFalseActivities": [
						{
							"name": "Set MonTexte",
							"type": "SetVariable",
							"dependsOn": [],
							"userProperties": [],
							"typeProperties": {
								"variableName": "MonTexte",
								"value": "truc"
							}
						}
					]
				}
			}
		],
		"variables": {
			"MonTexte": {
				"type": "String",
				"defaultValue": "Texte dans ma variable"
			},
			"MonTableau": {
				"type": "Array"
			}
		},
		"annotations": [
			"Mon annotation"
		],
		"lastPublishTime": "2020-08-09T09:44:48Z"
	},
	"type": "Microsoft.DataFactory/factories/pipelines"
}